setup.py
ease/__init__.py
ease/create.py
ease/essay_set.py
ease/feature_extractor.py
ease/grade.py
ease/model_creator.py
ease/predictor_extractor.py
ease/predictor_set.py
ease/util_functions.py
ease.egg-info/PKG-INFO
ease.egg-info/SOURCES.txt
ease.egg-info/dependency_links.txt
ease.egg-info/top_level.txt
ease/data/__init__.py
ease/external_code/__init__.py