Metadata-Version: 1.0
Name: ease
Version: 0.1.1
Summary: Machine learning based automated text classification library.  Useful for essay scoring and other tasks.  Please see https://github.com/edx/discern for an API wrapper of this code.
Home-page: https://github.com/edx/ease
Author: Vik Paruchuri
Author-email: vik@edx.org
License: AGPL
Keywords: ml machine learning nlp essay education
Platform: UNKNOWN
